{
  "total_profiles": 35,
  "profiles": [
    {
      "id": 1,
      "name": "General Strength",
      "slug": "general-strength",
      "domain": "strength",
      "axis_bias": "🏛",
      "gold_affinity": false,
      "exercise_count": 3270,
      "zip_count": 48,
      "working_count": 35,
      "bonus_count": 13
    },
    {
      "id": 2,
      "name": "Powerlifting",
      "slug": "powerlifting",
      "domain": "strength",
      "axis_bias": "🏛",
      "gold_affinity": false,
      "exercise_count": 3270,
      "zip_count": 48,
      "working_count": 35,
      "bonus_count": 13
    },
    {
      "id": 3,
      "name": "Strongman / Odd Object",
      "slug": "strongman",
      "domain": "strength",
      "axis_bias": "🔨",
      "gold_affinity": true,
      "exercise_count": 3270,
      "zip_count": 48,
      "working_count": 35,
      "bonus_count": 13
    },
    {
      "id": 4,
      "name": "Calisthenics Strength",
      "slug": "calisthenics-strength",
      "domain": "strength",
      "axis_bias": "🪐",
      "gold_affinity": false,
      "exercise_count": 3270,
      "zip_count": 48,
      "working_count": 35,
      "bonus_count": 13
    },
    {
      "id": 5,
      "name": "Kettlebell Strength",
      "slug": "kettlebell-strength",
      "domain": "strength",
      "axis_bias": "🔨",
      "gold_affinity": false,
      "exercise_count": 3270,
      "zip_count": 48,
      "working_count": 35,
      "bonus_count": 13
    },
    {
      "id": 6,
      "name": "Senior Strength",
      "slug": "senior-strength",
      "domain": "strength",
      "axis_bias": "🏛",
      "gold_affinity": false,
      "exercise_count": 3270,
      "zip_count": 48,
      "working_count": 35,
      "bonus_count": 13
    },
    {
      "id": 7,
      "name": "Post-Rehab Strength",
      "slug": "post-rehab-strength",
      "domain": "strength",
      "axis_bias": "🏛",
      "gold_affinity": false,
      "exercise_count": 3270,
      "zip_count": 48,
      "working_count": 35,
      "bonus_count": 13
    },
    {
      "id": 8,
      "name": "Bodybuilding",
      "slug": "bodybuilding",
      "domain": "hypertrophy",
      "axis_bias": "🌹",
      "gold_affinity": false,
      "exercise_count": 3270,
      "zip_count": 48,
      "working_count": 35,
      "bonus_count": 13
    },
    {
      "id": 9,
      "name": "Physique / Recomp",
      "slug": "physique-recomp",
      "domain": "hypertrophy",
      "axis_bias": "🌹",
      "gold_affinity": false,
      "exercise_count": 3270,
      "zip_count": 48,
      "working_count": 35,
      "bonus_count": 13
    },
    {
      "id": 10,
      "name": "Athletic Hypertrophy",
      "slug": "athletic-hypertrophy",
      "domain": "hypertrophy",
      "axis_bias": "🔨",
      "gold_affinity": false,
      "exercise_count": 3270,
      "zip_count": 48,
      "working_count": 35,
      "bonus_count": 13
    },
    {
      "id": 11,
      "name": "Minimalist Hypertrophy",
      "slug": "minimalist-hypertrophy",
      "domain": "hypertrophy",
      "axis_bias": "🏛",
      "gold_affinity": false,
      "exercise_count": 3270,
      "zip_count": 48,
      "working_count": 35,
      "bonus_count": 13
    },
    {
      "id": 12,
      "name": "Aesthetic Specialization",
      "slug": "aesthetic-specialization",
      "domain": "hypertrophy",
      "axis_bias": "🌹",
      "gold_affinity": false,
      "exercise_count": 3270,
      "zip_count": 48,
      "working_count": 35,
      "bonus_count": 13
    },
    {
      "id": 13,
      "name": "General Conditioning",
      "slug": "general-conditioning",
      "domain": "conditioning",
      "axis_bias": "⌛",
      "gold_affinity": false,
      "exercise_count": 3270,
      "zip_count": 48,
      "working_count": 35,
      "bonus_count": 13
    },
    {
      "id": 14,
      "name": "Marathon / Distance Running",
      "slug": "marathon-distance",
      "domain": "conditioning",
      "axis_bias": "⌛",
      "gold_affinity": false,
      "exercise_count": 3270,
      "zip_count": 48,
      "working_count": 35,
      "bonus_count": 13
    },
    {
      "id": 15,
      "name": "Sprint / Power Conditioning",
      "slug": "sprint-power-conditioning",
      "domain": "conditioning",
      "axis_bias": "⌛",
      "gold_affinity": true,
      "exercise_count": 3270,
      "zip_count": 48,
      "working_count": 35,
      "bonus_count": 13
    },
    {
      "id": 16,
      "name": "Sport Conditioning",
      "slug": "sport-conditioning",
      "domain": "conditioning",
      "axis_bias": "🔨",
      "gold_affinity": false,
      "exercise_count": 3270,
      "zip_count": 48,
      "working_count": 35,
      "bonus_count": 13
    },
    {
      "id": 17,
      "name": "Fasting Cardio + Strength",
      "slug": "fasting-cardio-strength",
      "domain": "conditioning",
      "axis_bias": "🏛",
      "gold_affinity": false,
      "exercise_count": 3270,
      "zip_count": 48,
      "working_count": 35,
      "bonus_count": 13
    },
    {
      "id": 18,
      "name": "General Functional Fitness",
      "slug": "general-functional",
      "domain": "functional",
      "axis_bias": "🔨",
      "gold_affinity": false,
      "exercise_count": 3270,
      "zip_count": 48,
      "working_count": 35,
      "bonus_count": 13
    },
    {
      "id": 19,
      "name": "CrossFit-Style",
      "slug": "crossfit-style",
      "domain": "functional",
      "axis_bias": "⌛",
      "gold_affinity": true,
      "exercise_count": 3270,
      "zip_count": 48,
      "working_count": 35,
      "bonus_count": 13
    },
    {
      "id": 20,
      "name": "Combat Sport Prep",
      "slug": "combat-sport-prep",
      "domain": "functional",
      "axis_bias": "🔨",
      "gold_affinity": false,
      "exercise_count": 3270,
      "zip_count": 48,
      "working_count": 35,
      "bonus_count": 13
    },
    {
      "id": 21,
      "name": "Field Sport Athlete",
      "slug": "field-sport-athlete",
      "domain": "functional",
      "axis_bias": "🔨",
      "gold_affinity": true,
      "exercise_count": 3270,
      "zip_count": 48,
      "working_count": 35,
      "bonus_count": 13
    },
    {
      "id": 22,
      "name": "Climbing / Grip Sport",
      "slug": "climbing-grip",
      "domain": "functional",
      "axis_bias": "🔨",
      "gold_affinity": false,
      "exercise_count": 3270,
      "zip_count": 48,
      "working_count": 35,
      "bonus_count": 13
    },
    {
      "id": 23,
      "name": "New to Gym",
      "slug": "new-to-gym",
      "domain": "life-stage",
      "axis_bias": "🏛",
      "gold_affinity": false,
      "exercise_count": 3270,
      "zip_count": 48,
      "working_count": 35,
      "bonus_count": 13
    },
    {
      "id": 24,
      "name": "Return After Break",
      "slug": "return-after-break",
      "domain": "life-stage",
      "axis_bias": "🏛",
      "gold_affinity": false,
      "exercise_count": 3270,
      "zip_count": 48,
      "working_count": 35,
      "bonus_count": 13
    },
    {
      "id": 25,
      "name": "50+ Active Living",
      "slug": "fifty-plus",
      "domain": "life-stage",
      "axis_bias": "🏛",
      "gold_affinity": false,
      "exercise_count": 3270,
      "zip_count": 48,
      "working_count": 35,
      "bonus_count": 13
    },
    {
      "id": 26,
      "name": "Pre/Post Natal",
      "slug": "pre-post-natal",
      "domain": "life-stage",
      "axis_bias": "🌹",
      "gold_affinity": false,
      "exercise_count": 3270,
      "zip_count": 48,
      "working_count": 35,
      "bonus_count": 13
    },
    {
      "id": 27,
      "name": "Youth Athletic Development",
      "slug": "youth-athletic",
      "domain": "life-stage",
      "axis_bias": "🔨",
      "gold_affinity": false,
      "exercise_count": 3270,
      "zip_count": 48,
      "working_count": 35,
      "bonus_count": 13
    },
    {
      "id": 28,
      "name": "Active Recovery",
      "slug": "active-recovery",
      "domain": "recovery",
      "axis_bias": "🌹",
      "gold_affinity": false,
      "exercise_count": 3270,
      "zip_count": 48,
      "working_count": 35,
      "bonus_count": 13
    },
    {
      "id": 29,
      "name": "Stress Management",
      "slug": "stress-management",
      "domain": "recovery",
      "axis_bias": "🌹",
      "gold_affinity": false,
      "exercise_count": 3270,
      "zip_count": 48,
      "working_count": 35,
      "bonus_count": 13
    },
    {
      "id": 30,
      "name": "Flexibility / Mobility",
      "slug": "flexibility-mobility",
      "domain": "recovery",
      "axis_bias": "🌹",
      "gold_affinity": false,
      "exercise_count": 3270,
      "zip_count": 48,
      "working_count": 35,
      "bonus_count": 13
    },
    {
      "id": 31,
      "name": "Injury Prevention / Prehab",
      "slug": "injury-prevention",
      "domain": "recovery",
      "axis_bias": "🔨",
      "gold_affinity": false,
      "exercise_count": 3270,
      "zip_count": 48,
      "working_count": 35,
      "bonus_count": 13
    },
    {
      "id": 32,
      "name": "Olympic Lifting",
      "slug": "olympic-lifting",
      "domain": "specialty",
      "axis_bias": "🪐",
      "gold_affinity": true,
      "exercise_count": 3270,
      "zip_count": 48,
      "working_count": 35,
      "bonus_count": 13
    },
    {
      "id": 33,
      "name": "Endurance Sport Cross-Training",
      "slug": "endurance-cross-training",
      "domain": "specialty",
      "axis_bias": "🔨",
      "gold_affinity": false,
      "exercise_count": 3270,
      "zip_count": 48,
      "working_count": 35,
      "bonus_count": 13
    },
    {
      "id": 34,
      "name": "Tactical / First Responder",
      "slug": "tactical-first-responder",
      "domain": "specialty",
      "axis_bias": "🔨",
      "gold_affinity": false,
      "exercise_count": 3270,
      "zip_count": 48,
      "working_count": 35,
      "bonus_count": 13
    },
    {
      "id": 35,
      "name": "Explorer / Outdoor Athlete",
      "slug": "explorer-outdoor",
      "domain": "specialty",
      "axis_bias": "🔨",
      "gold_affinity": false,
      "exercise_count": 3270,
      "zip_count": 48,
      "working_count": 35,
      "bonus_count": 13
    }
  ]
}