{"address":{"zip_emoji":"🏟🔨➖🔴","zip_numeric":"4255","order":{"emoji":"🏟","name":"Performance","index":3,"classical":"Corinthian"},"axis":{"emoji":"🔨","name":"Functional","index":1,"latin":"Utilitas"},"type":{"emoji":"➖","name":"Ultra","index":4,"muscles":["cardiovascular system"]},"color":{"emoji":"🔴","name":"Intense","index":4,"tier":"2-4","gold":true,"polarity":"expressive"},"operator":{"emoji":"🥨","name":"tendo","house":"The Extenders"},"deck":20,"url":"/zip/4255"},"architecture":{"D":"1.125rem","column_ratio":10,"intercolumniation":2.0,"superposition":1.0,"line_multiplier":1.5,"material":{"name":"White marble + gilding","hue":0,"sat":0,"warmth":0.5,"texture":"mirror-polished","shadow":"high contrast, theatrical"},"atmosphere":{"name":"Workshop","brightness":0.95,"hue_shift":0,"sat_multiplier":0.85,"warmth_modifier":0.0},"shadow":{"depth_multiplier":1.5,"hue":180,"saturation":10,"character":"high contrast, theatrical"}},"palette":{"active_register":"cathedral","light_register":{"name":"watercolor","philosophy":"Transparent glazed layers over a bright ground. Selective saturation. Paper showing through.","primary":"#C0392B","secondary":"#D44433","background":"#FDF0EE","surface":"#FFFFFF","text":"#5C1A13","accent":"#962D22","border":"#F0BCBA","type_accent":"#65a9cc","operator_tint":"#c54c39","saturation_level":0.76,"contrast_ratio":11.7},"dark_register":{"name":"cathedral","philosophy":"Warm pools of light on dark surfaces. Selective illumination. Stone walls absorbing candlelight.","cathedral_character":"Grand cathedral nave. Spotlit altar. Maximum drama.","primary":"#da7c5c","secondary":"#d56b47","background":"#121111","surface":"#1a1818","text":"#d7d2ca","accent":"#b06239","border":"#282424","type_accent":"#9ec9de","operator_tint":"#dc9387","saturation_level":0.494,"contrast_ratio":12.5},"color_wheel":{"hue":5.6,"saturation":63.4,"lightness":46.1,"complement_hue":185.6,"split_complements":[155.6,215.6],"analogous":[35.6,335.6]}},"typography":{"font_family":"'Inter', 'Helvetica Neue', sans-serif","font_character":"Condensed sans-serif. Utilitarian. Compact.","body_size":"1.125rem","display_size":"2.5rem","font_weight_body":800,"font_weight_display":900,"letter_spacing":"0em","line_height":1.35,"density":"sparse","tonal_register":{"name":"intense","character":"Testing environment. Maximum signal, no noise. Number forward. Everything else removed."}},"personality":{"house":{"primary":{"emoji":"🥨","name":"tendo","guild":"The Extenders","similarity":0.6931},"secondary":{"emoji":"🏹","name":"unknown","guild":"The Launchers","similarity":0.6212},"tertiary":{"emoji":"✍️","name":"unknown","guild":"The Scribes","similarity":0.5637},"anti":{"emoji":"👀","name":"specio","guild":"The Observers","similarity":-0.036}},"neighborhood":{"abacus_memberships":[{"id":8,"name":"Bodybuilding","domain":"hypertrophy","slot":"working","slot_number":20},{"id":21,"name":"Field Sport Athlete","domain":"functional","slot":"working","slot_number":20}],"primary_abacus":{"id":8,"name":"Bodybuilding","domain":"hypertrophy","slot":"working","slot_number":20}},"city_position":{"building":"Performance Hall (Corinthian)","floor":"Utilitas (Functional)","wing":"Ultra Wing","room":"Intense Room"},"difficulty_class":5,"cns_demand":"high"},"connections":{"navigation":{"N":"5245","E":"4215","S":"3235","W":"4325"},"same_deck_zips":39,"junction_suggestions":["4256","4254","4245"],"abacus_membership":[{"id":8,"name":"Bodybuilding","domain":"hypertrophy","slot":"working","slot_number":20},{"id":21,"name":"Field Sport Athlete","domain":"functional","slot":"working","slot_number":20}],"cosine_nearest_5":["4256","4254","4245","4253","4455"],"cosine_farthest":"1311"},"metadata":{"deck":20,"deck_name":"🏟🔨 Performance Functional","operator_default":{"emoji":"🥨","name":"tendo"},"block_sequence":["♨️","🪜","🧈","🚂","🧮"],"block_count":5,"weight_vector":[-6,-1,-1,6,8,8,-8,-6,8,-4,8,6,0,0,0,0,0,8,-3,-6,4,8,8,8,0,-6,7,0,0,8,0,0,0,0,8,5,-7,3,-8,-8,0,-7,4,0,0,0,6,0,0,0,4,0,1,8,5,8,5,0,0,0,8],"vector_magnitude":39.79}}