{"address":{"zip_emoji":"🖼⌛➖🔵","zip_numeric":"7553","order":{"emoji":"🖼","name":"Restoration","index":6,"classical":"Palladian"},"axis":{"emoji":"⌛","name":"Time","index":4,"latin":"Temporitas"},"type":{"emoji":"➖","name":"Ultra","index":4,"muscles":["cardiovascular system"]},"color":{"emoji":"🔵","name":"Structured","index":2,"tier":"2-3","gold":false,"polarity":"expressive"},"operator":{"emoji":"✒️","name":"grapho","house":"The Scribes"},"deck":41,"url":"/zip/7553"},"architecture":{"D":"1.0625rem","column_ratio":9.5,"intercolumniation":3.0,"superposition":0.7,"line_multiplier":0.6,"material":{"name":"Stucco + fresco","hue":40,"sat":15,"warmth":0.8,"texture":"chalky, soft","shadow":"almost none, flat"},"atmosphere":{"name":"Clock tower","brightness":1.0,"hue_shift":-10,"sat_multiplier":1.0,"warmth_modifier":0.0},"shadow":{"depth_multiplier":0.6,"hue":30,"saturation":8,"character":"almost none, flat"}},"palette":{"active_register":"user_preference","light_register":{"name":"watercolor","philosophy":"Transparent glazed layers over a bright ground. Selective saturation. Paper showing through.","primary":"#2E6BA6","secondary":"#3A7EC0","background":"#EDF4FB","surface":"#FFFFFF","text":"#143050","accent":"#1E4F7D","border":"#B8D4EC","type_accent":"#65a9cc","operator_tint":"#2c3352","saturation_level":0.68,"contrast_ratio":12.1},"dark_register":{"name":"cathedral","philosophy":"Warm pools of light on dark surfaces. Selective illumination. Stone walls absorbing candlelight.","cathedral_character":"Dimmed fresco chapel. Frescoes barely visible in candlelight. Serene.","primary":"#517cce","secondary":"#3d6cc8","background":"#131210","surface":"#1b1a17","text":"#d7d2ca","accent":"#334e99","border":"#2a2722","type_accent":"#9ec9de","operator_tint":"#4f5c94","saturation_level":0.442,"contrast_ratio":12.4},"color_wheel":{"hue":209.5,"saturation":56.6,"lightness":41.6,"complement_hue":29.5,"split_complements":[359.5,59.5],"analogous":[239.5,179.5]}},"typography":{"font_family":"'Inter', 'Helvetica Neue', sans-serif","font_character":"Monospace accents. Tabular. Precise.","body_size":"1.0625rem","display_size":"1.75rem","font_weight_body":300,"font_weight_display":400,"letter_spacing":"0.03em","line_height":1.85,"density":"airy","tonal_register":{"name":"structured","character":"Recovery posture. Maximum whitespace. Slow, breath-paced rhythm."}},"personality":{"house":{"primary":{"emoji":"🎻","name":"unknown","guild":"The Conductors","similarity":0.7085},"secondary":{"emoji":"✍️","name":"unknown","guild":"The Scribes","similarity":0.59},"tertiary":{"emoji":"👀","name":"specio","guild":"The Observers","similarity":0.5332},"anti":{"emoji":"🤌","name":"facio","guild":"The Executors","similarity":0.2097}},"neighborhood":{"abacus_memberships":[{"id":13,"name":"General Conditioning","domain":"conditioning","slot":"bonus","bonus_role":"variety"}],"primary_abacus":{"id":13,"name":"General Conditioning","domain":"conditioning","slot":"bonus","bonus_role":"variety"}},"city_position":{"building":"Restoration Hall (Palladian)","floor":"Temporitas (Time)","wing":"Ultra Wing","room":"Structured Room"},"difficulty_class":2,"cns_demand":"low"},"connections":{"navigation":{"N":"7543","E":"7513","S":"6533","W":"7623"},"same_deck_zips":39,"junction_suggestions":["7558","7453","7554"],"abacus_membership":[{"id":13,"name":"General Conditioning","domain":"conditioning","slot":"bonus","bonus_role":"variety"}],"cosine_nearest_5":["7558","7453","7554","7556","7353"],"cosine_farthest":"2145"},"metadata":{"deck":41,"deck_name":"🖼⌛ Restoration Time","operator_default":{"emoji":"✒️","name":"grapho"},"block_sequence":["🎯","🪫","🧈","🧬","🚂","🧮"],"block_count":6,"weight_vector":[0,-7,0,-8,4,4,8,-3,0,5,-6,8,0,0,0,0,0,8,0,5,8,0,-7,8,-3,8,0,8,0,8,0,-4,0,0,1,0,0,-8,-4,-4,0,3,6,-3,0,4,8,0,0,5,8,5,0,8,3,0,0,0,5,5,-7],"vector_magnitude":36.65}}